LICENSE
MANIFEST.in
README.rst
setup.py
django_blog_app.egg-info/PKG-INFO
django_blog_app.egg-info/SOURCES.txt
django_blog_app.egg-info/dependency_links.txt
django_blog_app.egg-info/top_level.txt
migrations/0001_initial.py
migrations/0002_auto_20160110_2000.py
migrations/0003_post_tags.py
migrations/0004_review.py
migrations/0005_auto_20160502_1007.py
migrations/0006_auto_20160502_1013.py
migrations/0007_review_review_banner.py
migrations/0008_auto_20160507_1744.py
migrations/0009_auto_20160507_1750.py
migrations/0010_auto_20160511_0722.py
migrations/0011_review_tracking_link.py
migrations/0012_post_meta_keywords.py
migrations/0013_auto_20160514_1655.py
migrations/0014_auto_20160514_1907.py
migrations/0015_auto_20160514_1922.py
migrations/0016_auto_20160514_1929.py
migrations/0017_review_slider.py
migrations/0018_auto_20160517_1751.py
migrations/0019_games.py
migrations/0020_auto_20160522_1805.py
migrations/0021_auto_20160522_1811.py
migrations/0022_post_post_type.py
migrations/0023_auto_20160525_0235.py
migrations/0024_review_featured_text.py
migrations/0025_auto_20160611_1046.py
migrations/__init__.py
templatetags/__init__.py
templatetags/blog_tags.py